setup.py
paquete/__init__.py
paquete/adios/__init__.py
paquete/adios/despedida.py
paquete/hola/__init__.py
paquete/hola/saludos.py
paquete_pino.egg-info/PKG-INFO
paquete_pino.egg-info/SOURCES.txt
paquete_pino.egg-info/dependency_links.txt
paquete_pino.egg-info/top_level.txt