Metadata-Version: 2.1
Name: paquete-pino
Version: 0.1
Summary: Este es un paquete ejemplo
Home-page: UNKNOWN
Author: jpino
Author-email: jpinoc@gmail.com
License: UNKNOWN
Platform: UNKNOWN
